pixasonics/__init__.py
pixasonics/core.py
pixasonics/features.py
pixasonics/launch.py
pixasonics/pixasonics_tutorial.ipynb
pixasonics/synths.py
pixasonics/ui.py
pixasonics/utils.py
pixasonics/figures/.DS_Store
pixasonics/figures/Pixasonics_gist_2.8.png
pixasonics/figures/Pixasonics_structure_v3.png
pixasonics/figures/feature_ui_example_meanpix.png
pixasonics/figures/feature_ui_example_meanred.png
pixasonics/figures/interface_screenshot_2.png
pixasonics/figures/mapper_ui_example.png
pixasonics/figures/osc_example_max_patch.png
pixasonics/figures/synth_ui_example.png
pixasonics/figures/synth_ui_example_multichannel.png
pixasonics/images/.DS_Store
pixasonics/images/test.jpg
pixasonics/images/cellular_dataset/.DS_Store
pixasonics/images/cellular_dataset/merged_8bit/Timepoint_001_220518-ST_C03_s1.jpg
pixasonics/images/cellular_dataset/merged_8bit/Timepoint_002_220518-ST_C03_s1.jpg
pixasonics/images/cellular_dataset/merged_8bit/Timepoint_003_220518-ST_C03_s1.jpg
pixasonics/images/cellular_dataset/merged_8bit/Timepoint_004_220518-ST_C03_s1.jpg
pixasonics/images/cellular_dataset/merged_8bit/Timepoint_005_220518-ST_C03_s1.jpg
pixasonics/images/cellular_dataset/single_channel_16bit/Timepoint_001_220518-ST_C03_s1_w1.TIF
pixasonics/images/cellular_dataset/single_channel_16bit/Timepoint_001_220518-ST_C03_s1_w2.TIF
pixasonics/images/cellular_dataset/single_channel_16bit/Timepoint_001_220518-ST_C03_s1_w3.TIF
pixasonics/images/cellular_dataset/single_channel_16bit/Timepoint_002_220518-ST_C03_s1_w1.TIF
pixasonics/images/cellular_dataset/single_channel_16bit/Timepoint_002_220518-ST_C03_s1_w2.TIF
pixasonics/images/cellular_dataset/single_channel_16bit/Timepoint_002_220518-ST_C03_s1_w3.TIF
pixasonics/images/cellular_dataset/single_channel_16bit/Timepoint_003_220518-ST_C03_s1_w1.TIF
pixasonics/images/cellular_dataset/single_channel_16bit/Timepoint_003_220518-ST_C03_s1_w2.TIF
pixasonics/images/cellular_dataset/single_channel_16bit/Timepoint_003_220518-ST_C03_s1_w3.TIF
pixasonics-0.1.6.dist-info/licenses/LICENSE
pixasonics-0.1.6.dist-info/METADATA
pixasonics-0.1.6.dist-info/WHEEL
pixasonics-0.1.6.dist-info/entry_points.txt
pixasonics-0.1.6.dist-info/top_level.txt
pixasonics-0.1.6.dist-info/RECORD
