Metadata-Version: 2.4
Name: pixasonics
Version: 0.1.6
Summary: An Image Sonification Toolbox
Home-page: https://github.com/balintlaczko/pixasonics
Author: Balint Laczko
Author-email: balint.laczko@imv.uio.no
Classifier: Development Status :: 3 - Alpha
Classifier: Intended Audience :: Developers
Classifier: License :: OSI Approved :: GNU General Public License v3 (GPLv3)
Classifier: Programming Language :: Python :: 3.10
Classifier: Programming Language :: Python :: 3.11
Classifier: Programming Language :: Python :: 3.12
License-File: LICENSE
Requires-Dist: numpy
Requires-Dist: numba
Requires-Dist: pillow
Requires-Dist: signalflow
Requires-Dist: ipython
Requires-Dist: jupyter
Requires-Dist: ipycanvas
Requires-Dist: ipywidgets
Dynamic: author
Dynamic: author-email
Dynamic: classifier
Dynamic: description
Dynamic: description-content-type
Dynamic: home-page
Dynamic: license-file
Dynamic: requires-dist
Dynamic: summary
